scraper_ignite/__init__.py
scraper_ignite/scraper_template.py
scraper_ignite-0.1.1.dist-info/METADATA
scraper_ignite-0.1.1.dist-info/WHEEL
scraper_ignite-0.1.1.dist-info/entry_points.txt
scraper_ignite-0.1.1.dist-info/top_level.txt
scraper_ignite-0.1.1.dist-info/RECORD
