Metadata-Version: 2.2
Name: scraper_ignite
Version: 0.1.1
Summary: A simple Scraper template creator
Home-page: https://github.com/nahom-d54/scraper-ignite
Author: Nahom D
Author-email: nahom@nahom.eu.org
License: MIT
Classifier: Programming Language :: Python :: 3
Classifier: License :: OSI Approved :: MIT License
Classifier: Operating System :: OS Independent
Requires-Python: >=3.7
Requires-Dist: httpx
Requires-Dist: bs4
Dynamic: author
Dynamic: author-email
Dynamic: classifier
Dynamic: description
Dynamic: description-content-type
Dynamic: home-page
Dynamic: requires-dist
Dynamic: requires-python
Dynamic: summary
